petrone_v2/__init__.py
petrone_v2/crc.py
petrone_v2/drone.py
petrone_v2/protocol.py
petrone_v2/receiver.py
petrone_v2/storage.py
petrone_v2/system.py
petrone_v2-0.1.81.dist-info/DESCRIPTION.rst
petrone_v2-0.1.81.dist-info/METADATA
petrone_v2-0.1.81.dist-info/RECORD
petrone_v2-0.1.81.dist-info/WHEEL
petrone_v2-0.1.81.dist-info/metadata.json
petrone_v2-0.1.81.dist-info/top_level.txt
