Metadata-Version: 2.0
Name: petrone-v2
Version: 0.1.81
Summary: Library for BYROBOT PETRONE V2
Home-page: http://www.byrobot.co.kr
Author: BYROBOT
Author-email: dev@byrobot.co.kr
License: UNKNOWN
Platform: UNKNOWN
Requires-Dist: colorama
Requires-Dist: numpy
Requires-Dist: pyserial
